pynagmailplugins-0.0.8-nspkg.pth
snowpenguin/nagmail/postfix.py
snowpenguin/nagmail/__init__.py
snowpenguin/nagmail/exim.py
snowpenguin/nagmail/common.py
snowpenguin/nagmail/nagios.py
pynagmailplugins-0.0.8.dist-info/top_level.txt
pynagmailplugins-0.0.8.dist-info/namespace_packages.txt
pynagmailplugins-0.0.8.dist-info/WHEEL
pynagmailplugins-0.0.8.dist-info/metadata.json
pynagmailplugins-0.0.8.dist-info/METADATA
pynagmailplugins-0.0.8.dist-info/RECORD
pynagmailplugins-0.0.8.dist-info/DESCRIPTION.rst
pynagmailplugins-0.0.8.data/scripts/pydnswl_check.py
pynagmailplugins-0.0.8.data/scripts/check_mailq.py
