Metadata-Version: 2.0
Name: pynagmailplugins
Version: 0.0.8
Summary: Nagios plugins that detect unusual mail flow.
Home-page: https://github.com/kbytesys/pynagmailplugins
Author: Andrea Briganti
Author-email: kbytesys@gmail.com
License: GNU GPL v2
Download-URL: https://github.com/kbytesys/pynagmailplugins/tarball/v0.0.8
Keywords: nagios,systemd,postfix,mail
Platform: UNKNOWN
Classifier: Development Status :: 2 - Pre-Alpha
Classifier: Environment :: Plugins
Classifier: Intended Audience :: System Administrators
Classifier: License :: OSI Approved :: GNU General Public License v2 (GPLv2)
Classifier: Programming Language :: Python
Classifier: Programming Language :: Python :: 3 :: Only
Classifier: Operating System :: POSIX :: Linux
Classifier: Topic :: System :: Networking :: Monitoring
Requires-Dist: nagiosplugin (>=1.2)
